Workbook

Sheet Financial Project
B1: Financial Plan
B2: Assumptions | D2: 2025 | E2: =+D2+1 -> 2026 | F2: =+E2+1 -> 2027 | G2: =+F2+1 -> 2028 | H2: =+G2+1 -> 2029 | I2: =+H2+1 -> 2030 | J2: =+I2+1 -> 2031 | K2: =+J2+1 -> 2032 | L2: =+K2+1 -> 2033 | M2: 2034 | N2: =+M2+1 -> 2035 | O2: =+N2+1 -> 2036 | P2: =+O2+1 -> 2037 | Q2: =+P2+1 -> 2038 | R2: =+Q2+1 -> 2039 | S2: =+R2+1 -> 2040 | T2: =+S2+1 -> 2041 | U2: =+T2+1 -> 2042 | ... AU2: =+AT2+1 -> 2068 | AV2: Total
B3: Annual Pay Increase-Wife | D3: 0.05 | E3: 0.05 | F3: 0.04 | G3: 0.04 | H3: 0.04 | I3: 0.04 | J3: 0.04 | K3: 0.04 | L3: 0.04 | M3: 0.04 | N3: 0.04 | O3: 0.04 | P3: 0.04 | Q3: 0.025 | R3: 0.025 | S3: 0.025 | T3: 0.025 | U3: 0.025 | V3: 0.025 | W3: 0.025 | X3: 0.025 | Y3: 0.025 | Z3: 0.025 | AA3: 0.025 | AB3: 0.025 | AC3: 0.025 | AD3: 0.025 | AE3: 0.025 | AF3: 0.025 | AG3: 0.025 | AH3: 0.025 | AI3: 0.025
B4: Annual Pay Increase-Husband | D4: 0.025 | E4: 0.025 | F4: 0.025 | G4: 0.025 | H4: 0.025 | I4: 0.025 | J4: 0.025 | K4: 0.025 | L4: 0.025 | M4: 0.025 | N4: 0.025 | O4: 0.025 | P4: 0.025 | Q4: 0.025 | R4: 0.025 | S4: 0.025 | T4: 0.025 | U4: 0.025 | V4: 0.025 | W4: 0.025 | X4: 0.025 | Y4: 0.025 | Z4: 0.025 | AA4: 0.025
B5: Inflation | D5: 0.025 | E5: 0.025 | F5: 0.025 | G5: 0.025 | H5: 0.025 | I5: 0.025 | J5: 0.025 | K5: 0.025 | L5: 0.025 | M5: 0.025 | N5: 0.025 | O5: 0.025 | P5: 0.025 | Q5: 0.025 | R5: 0.025 | S5: 0.025 | T5: 0.025 | U5: 0.025 | V5: 0.025 | W5: 0.025 | X5: 0.025 | Y5: 0.025 | Z5: 0.025 | AA5: 0.025 | AB5: 0.025 | AC5: 0.025 | AD5: 0.025 | AE5: 0.025 | AF5: 0.025 | AG5: 0.025 | AH5: 0.025 | AI5: 0.025 | AJ5: 0.025 | AK5: 0.025 | AL5: 0.025 | AM5: 0.025 | AN5: 0.025 | AO5: 0.025 | AP5: 0.025 | AQ5: 0.025 | AR5: 0.025 | AS5: 0.025 | AT5: 0.025 | AU5: 0.025
B6: 401KContribution-Wife | D6: 0.15 | E6: 0.15 | F6: 0.15 | G6: 0.15 | H6: 0.15 | I6: 0.15 | J6: 0.15 | K6: 0.15 | L6: 0.15 | M6: 0.15 | N6: 0.15 | O6: 0.15 | P6: 0.15 | Q6: 0.15 | R6: 0.15 | S6: 0.15 | T6: 0.15 | U6: 0.15 | V6: 0.15 | W6: 0.15 | X6: 0.15 | Y6: 0.15 | Z6: 0.15 | AA6: 0.15 | AB6: 0.15 | AC6: 0.15 | AD6: 0.15 | AE6: 0.15 | AF6: 0.15 | AG6: 0.15
B7: 401K Contribution-Husband | D7: 0.1 | E7: 0.1 | F7: 0.15 | G7: 0.15 | H7: 0.15 | I7: 0.15 | J7: 0.15 | K7: 0.15 | L7: 0.15 | M7: 0.15 | N7: 0.15 | O7: 0.15 | P7: 0.15 | Q7: 0.15 | R7: 0.15 | S7: 0.15 | T7: 0.15 | U7: 0.15 | V7: 0.15 | W7: 0.15 | X7: 0.15 | Y7: 0.15 | Z7: 0.15 | AA7: 0.15
B8: 401K ROI-Wife | D8: 0.08 | E8: 0.08 | F8: 0.08 | G8: 0.08 | H8: 0.08 | I8: 0.08 | J8: 0.08 | K8: 0.08 | L8: 0.08 | M8: 0.08 | N8: 0.08 | O8: 0.08 | P8: 0.08 | Q8: 0.08 | R8: 0.08 | S8: 0.08 | T8: 0.08 | U8: 0.08 | V8: 0.08 | W8: 0.08 | X8: 0.08 | Y8: 0.08 | Z8: 0.08 | AA8: 0.08 | AB8: 0.08 | AC8: 0.08 | AD8: 0.08 | AE8: 0.08 | AF8: 0.08 | AG8: 0.08 | AH8: 0.08 | AI8: 0.08 | AJ8: 0.08 | AK8: 0.08 | AL8: 0.08 | AM8: 0.08 | AN8: 0.08 | AO8: 0.08 | AP8: 0.08 | AQ8: 0.08 | AR8: 0.08 | AS8: 0.08 | AT8: 0.08 | AU8: 0.08
B9: 401K ROI-Husband | D9: 0.08 | E9: 0.08 | F9: 0.08 | G9: 0.08 | H9: 0.08 | I9: 0.08 | J9: 0.08 | K9: 0.08 | L9: 0.08 | M9: 0.08 | N9: 0.08 | O9: 0.08 | P9: 0.08 | Q9: 0.06 | R9: 0.06 | S9: 0.06 | T9: 0.06 | U9: 0.06 | V9: 0.06 | W9: 0.06 | X9: 0.06 | Y9: 0.06 | Z9: 0.06 | AA9: 0.06 | AB9: 0.06 | AC9: 0.06 | AD9: 0.06 | AE9: 0.06 | AF9: 0.06 | AG9: 0.06 | AH9: 0.06 | AI9: 0.06 | AJ9: 0.06 | AK9: 0.06 | AL9: 0.06 | AM9: 0.06 | AN9: 0.06 | AO9: 0.06 | AP9: 0.06 | AQ9: 0.06 | AR9: 0.06 | AS9: 0.06 | AT9: 0.06 | AU9: 0.06
B10: Roth IRA-ROI | D10: 0.08 | E10: 0.08 | F10: 0.08 | G10: 0.08 | H10: 0.08 | I10: 0.08 | J10: 0.08 | K10: 0.08 | L10: 0.08 | M10: 0.08 | N10: 0.08 | O10: 0.08 | P10: 0.08 | Q10: 0.06 | R10: 0.06 | S10: 0.06 | T10: 0.06 | U10: 0.06 | V10: 0.06 | W10: 0.06 | X10: 0.06 | Y10: 0.06 | Z10: 0.06 | AA10: 0.06 | AB10: 0.06 | AC10: 0.06 | AD10: 0.06 | AE10: 0.06 | AF10: 0.06 | AG10: 0.06 | AH10: 0.06 | AI10: 0.06 | AJ10: 0.06 | AK10: 0.06 | AL10: 0.06 | AM10: 0.06 | AN10: 0.06 | AO10: 0.06 | AP10: 0.06 | AQ10: 0.06 | AR10: 0.06 | AS10: 0.06 | AT10: 0.06 | AU10: 0.06
B11: Traditional IRA-ROI | J11: 0.08 | K11: 0.08 | L11: 0.08 | M11: 0.08 | N11: 0.08 | O11: 0.08 | P11: 0.08 | Q11: 0.06 | R11: 0.06 | S11: 0.06 | T11: 0.06 | U11: 0.06 | V11: 0.06 | W11: 0.06 | X11: 0.06 | Y11: 0.06 | Z11: 0.06 | AA11: 0.06 | AB11: 0.06 | AC11: 0.06 | AD11: 0.06 | AE11: 0.06 | AF11: 0.06 | AG11: 0.06 | AH11: 0.06 | AI11: 0.06 | AJ11: 0.06 | AK11: 0.06 | AL11: 0.06 | AM11: 0.06 | AN11: 0.06 | AO11: 0.06 | AP11: 0.06 | AQ11: 0.06 | AR11: 0.06 | AS11: 0.06 | AT11: 0.06 | AU11: 0.06
B12: Mortgage Interest Rate | D12: 0.0825 | E12: 0.0825 | F12: 0.0825 | G12: 0.0825 | H12: 0.0825 | I12: 0.0825 | J12: 0.0825 | K12: 0.0825 | L12: 0.0825 | M12: 0.0825 | N12: 0.0825 | O12: 0.0825 | P12: 0.0825 | Q12: 0.0825 | R12: 0.0825 | S12: 0.0825 | T12: 0.0825 | U12: 0.0825 | V12: 0.0825 | W12: 0.0825 | X12: 0.0825 | Y12: 0.0825 | Z12: 0.0825 | AA12: 0.0825 | AB12: 0.0825 | AC12: 0.0825 | AD12: 0.0825 | AE12: 0.0825 | AF12: 0.0825 | AG12: 0.0825 | AH12: 0.0825 | AI12: 0.0825 | AJ12: 0.0825 | AK12: 0.0825 | AL12: 0.0825 | AM12: 0.0825 | AN12: 0.0825 | AO12: 0.0825 | AP12: 0.0825 | AQ12: 0.0825 | AR12: 0.0825 | AS12: 0.0825 | AT12: 0.0825 | AU12: 0.0825
B13: Mortgage Payment Year | D13: 15 | E13: =+D13-1 -> 14 | F13: =+E13-1 -> 13 | G13: =+F13-1 -> 12 | H13: =+G13-1 -> 11 | I13: =+H13-1 -> 10 | J13: =+I13-1 -> 9 | K13: =+J13-1 -> 8 | L13: =+K13-1 -> 7 | ... S13: =+R13-1 -> 0
B14: Saving/CD Rate | D14: 0.048 | E14: 0.048 | F14: 0.048 | G14: 0.048 | H14: 0.048 | I14: 0.048 | J14: 0.048 | K14: 0.048 | L14: 0.048 | M14: 0.048 | N14: 0.048 | O14: 0.048 | P14: 0.048 | Q14: 0.048 | R14: 0.048 | S14: 0.048 | T14: 0.048 | U14: 0.048 | V14: 0.048 | W14: 0.048 | X14: 0.048 | Y14: 0.048 | Z14: 0.048 | AA14: 0.048 | AB14: 0.048 | AC14: 0.048 | AD14: 0.048 | AE14: 0.048 | AF14: 0.048 | AG14: 0.048 | AH14: 0.048 | AI14: 0.048 | AJ14: 0.048 | AK14: 0.048 | AL14: 0.048 | AM14: 0.048 | AN14: 0.048 | AO14: 0.048 | AP14: 0.048 | AQ14: 0.048 | AR14: 0.048 | AS14: 0.048 | AT14: 0.048 | AU14: 0.048
B15: Payroll Tax % (includes all) | D15: 0.26 | E15: 0.26 | F15: 0.26 | G15: 0.26 | H15: 0.26 | I15: 0.26 | J15: 0.26 | K15: 0.26 | L15: 0.26 | M15: 0.26 | N15: 0.26 | O15: 0.26 | P15: 0.26 | Q15: 0.26 | R15: 0.26 | S15: 0.26 | T15: 0.26 | U15: 0.26 | V15: 0.26 | W15: 0.26 | X15: 0.26 | Y15: 0.26 | Z15: 0.26 | AA15: 0.26 | AB15: 0.26 | AC15: 0.26 | AD15: 0.26 | AE15: 0.26 | AF15: 0.26 | AG15: 0.26 | AH15: 0.26 | AI15: 0.26 | AJ15: 0.26 | AK15: 0.26 | AL15: 0.26 | AM15: 0.26 | AN15: 0.26 | AO15: 0.26 | AP15: 0.26 | AQ15: 0.26 | AR15: 0.26 | AS15: 0.26 | AT15: 0.26 | AU15: 0.26
B17: #Years until Retirement for Husband | D17: 22.5 | E17: =+D17-1 -> 21.5 | F17: =+E17-1 -> 20.5 | G17: =+F17-1 -> 19.5 | H17: =+G17-1 -> 18.5 | I17: =+H17-1 -> 17.5 | J17: =+I17-1 -> 16.5 | K17: =+J17-1 -> 15.5 | L17: =+K17-1 -> 14.5 | ... AU17: =+AT17-1 -> -20.5
B18: #Years until Retirement for Wife | D18: 28 | E18: =+D18-1 -> 27 | F18: =+E18-1 -> 26 | G18: =+F18-1 -> 25 | H18: =+G18-1 -> 24 | I18: =+H18-1 -> 23 | J18: =+I18-1 -> 22 | K18: =+J18-1 -> 21 | L18: =+K18-1 -> 20 | ... AU18: =+AT18-1 -> -15
B20: Income | D20: 2025 | E20: =+D20+1 -> 2026 | F20: =+E20+1 -> 2027 | G20: =+F20+1 -> 2028 | H20: =+G20+1 -> 2029 | I20: =+H20+1 -> 2030 | J20: =+I20+1 -> 2031 | K20: =+J20+1 -> 2032 | L20: =+K20+1 -> 2033 | ... AU20: =+AT20+1 -> 2068
B21: Wife Annual Income | D21: 55000 | E21: =+D21*(1+E3) -> 57750 | F21: =+E21*(1+F3) -> 60060 | G21: =+F21*(1+G3) -> 62462.4 | H21: =+G21*(1+H3) -> 64960.896 | I21: =+H21*(1+I3) -> 67559.332 | J21: =+I21*(1+J3) -> 70261.705 | K21: =+J21*(1+K3) -> 73072.173 | L21: =+K21*(1+L3) -> 75995.06 | ... AG21: =+AF21*(1+AG3) -> 135277.15 | AH21: 20000 | AI21: 20000 | AJ21: =+AI21*(1+AJ3) -> 20000 | AK21: =+AJ21*(1+AK3) -> 20000 | AL21: =+AK21*(1+AL3) -> 20000 | AM21: =+AL21*(1+AM3) -> 20000 | AN21: 0 | AO21: 0 | AP21: =+AO21*(1+AP3) -> 0 | AQ21: =+AP21*(1+AQ3) -> 0 | AR21: =+AQ21*(1+AR3) -> 0 | AS21: =+AR21*(1+AS3) -> 0 | AT21: =+AS21*(1+AT3) -> 0 | AU21: =+AT21*(1+AU3) -> 0 | AV21: =SUM(D21:AU21) -> 2944060.9
B22: Wife Bonus | D22: 1000 | E22: 2000 | F22: 2000 | G22: 2000 | H22: 2000 | I22: 2000 | J22: 2000 | K22: 2000 | L22: 2000 | M22: 2000 | N22: 2000 | O22: 2000 | P22: 2000 | Q22: 2000 | R22: 2000 | S22: 2000 | T22: 2000 | U22: 2000 | V22: 2000 | W22: 2000 | X22: 2000 | Y22: 2000 | Z22: 2000 | AA22: 2000 | AB22: 2000 | AC22: 2000 | AD22: 2000 | AE22: 2000 | AF22: 2000 | AG22: 2000 | AV22: =SUM(D22:AU22) -> 59000
B23: Husband Annual Income | D23: 100000 | E23: =+D23*(1+E4) -> 102500 | F23: =+E23*(1+F4) -> 105062.5 | G23: =+F23*(1+G4) -> 107689.06 | H23: =+G23*(1+H4) -> 110381.29 | I23: =+H23*(1+I4) -> 113140.82 | J23: =+I23*(1+J4) -> 115969.34 | K23: =+J23*(1+K4) -> 118868.58 | L23: =+K23*(1+L4) -> 121840.29 | ... V23: =+U23*(1+V4) -> 155965.87 | W23: 75000 | X23: =+W23*(1+X4) -> 76875 | Y23: =+X23*(1+Y4) -> 78796.875 | Z23: =+Y23*(1+Z4) -> 80766.797 | AA23: =+Z23*(1+AA4) -> 82785.967 | AB23: 25000 | AC23: =+AB23*(1+AC4) -> 25000 | AD23: 25000 | AE23: 0 | AF23: 0 | AG23: 0 | AH23: 0 | AI23: 0 | AJ23: 0 | AK23: 0 | AL23: 0 | AM23: 0 | AN23: 0 | AO23: 0 | AP23: 0 | AQ23: 0 | AR23: 0 | AS23: 0 | AT23: 0 | AU23: 0 | AV23: =SUM(D23:AU23) -> 2863825.4
B24: Husband Bonus | D24: 14500 | E24: 11500 | F24: 12000 | G24: 12500 | H24: 12.5 | I24: 12.55 | J24: 14000 | K24: 14500 | L24: 15000 | M24: 15000 | N24: 15000 | O24: 16000 | P24: 16000 | Q24: 16000 | R24: 16000 | S24: 16500 | T24: 16500 | U24: 17000 | V24: 17000 | W24: 0 | X24: 0 | Y24: 0 | Z24: 0 | AA24: 0 | AB24: 0 | AC24: 0 | AV24: =SUM(D24:AU24) -> 255025.05
B25: Wife SS Payment | AJ25: 16140 | AK25: 16140 | AL25: 16140 | AM25: 16140 | AN25: 16140 | AO25: 16140 | AP25: 16140 | AQ25: 16140 | AR25: 16140 | AS25: 16140 | AT25: 16140 | AU25: 16140 | AV25: =SUM(D25:AU25) -> 193680
B26: Wife SS Payment | V26: 18620 | W26: 18620 | X26: 18620 | Y26: 18620 | Z26: 18620 | AA26: 18620 | AB26: 18620 | AC26: 18620 | AD26: 18620 | AE26: 18620 | AF26: 18620 | AG26: 18620 | AH26: 18620 | AI26: 18620 | AJ26: 18620 | AK26: 18620 | AV26: =SUM(D25:AU25) -> 193680
B27: 401K Withdrawal | AH27: 80000 | AI27: 80000 | AJ27: 80000 | AK27: 150000 | AL27: 150000 | AM27: 150000 | AN27: 150000 | AO27: 170000 | AP27: 250000 | AQ27: 2.525 | AR27: 2.55 | AS27: 2.575 | AT27: 400000 | AU27: 410000 | AV27: =SUM(D27:AU27) -> 2070007.6
B28: IRA Withdrawal Taxable | AH28: 15000 | AI28: 20000 | AJ28: 20000 | AK28: 5000 | AL28: 35000 | AM28: 40000 | AN28: 65000 | AO28: 48283
B29: IRA Withdrawal Non Taxable | AG29: 10000 | AH29: 50000 | AI29: 50000 | AJ29: 40665 | AK29: 50000 | AL29: 50000 | AM29: 50000 | AN29: 50000 | AO29: 50000 | AP29: 50000
B31: Total Income | D31: =SUM(D21:D30) -> 170500 | E31: =SUM(E21:E30) -> 173750 | F31: =SUM(F21:F30) -> 179122.5 | G31: =SUM(G21:G30) -> 184651.46 | H31: =SUM(H21:H30) -> 177354.69 | I31: =SUM(I21:I30) -> 182712.7 | J31: =SUM(J21:J30) -> 202231.05 | K31: =SUM(K21:K30) -> 208440.75 | ... AU31: =SUM(AU21:AU30) -> 426140 | AV31: =SUM(D31:AU31) -> 9382467
B33: Expenses
B34: Total Payroll Taxes | D34: =+(D31-D25-D25-D29)*D15 -> 44330 | E34: =+(E31-E25-E25-E29)*E15 -> 45175 | F34: =+(F31-F25-F25-F29)*F15 -> 46571.85 | G34: =+(G31-G25-G25-G29)*G15 -> 48009.38 | H34: =+(H31-H25-H25-H29)*H15 -> 46112.218 | I34: =+(I31-I25-I25-I29)*I15 -> 47505.303 | J34: =+(J31-J25-J25-J29)*J15 -> 52580.072 | K34: =+(K31-K25-K25-K29)*K15 -> 54194.595 | ... AU34: =+(AU31-AU25-AU25-AU29)*AU15 -> 102403.6 | AV34: =SUM(D34:AU34) -> 2221554.9
B35: Property Taxes | D35: 5500 | E35: =+D34*(1+E5) -> 45438.25 | F35: =+E34*(1+F5) -> 46304.375 | G35: =+F34*(1+G5) -> 47736.146 | H35: =+G34*(1+H5) -> 49209.615 | I35: =+H34*(1+I5) -> 47265.024 | J35: =+I34*(1+J5) -> 48692.935 | K35: =+J34*(1+K5) -> 53894.574 | L35: =+K34*(1+L5) -> 55549.46 | ... AU35: =+AT34*(1+AU5) -> 102298.69 | AV35: =SUM(D34:AU34) -> 2221554.9
B36: 401K Contribution-Wife | D36: =(+D21+D22)*D6 -> 8400 | E36: =(+E21+E22)*E6 -> 8962.5 | F36: =(+F21+F22)*F6 -> 9309 | G36: =(+G21+G22)*G6 -> 9669.36 | H36: =(+H21+H22)*H6 -> 10044.134 | I36: =(+I21+I22)*I6 -> 10433.9 | J36: =(+J21+J22)*J6 -> 10839.256 | K36: =(+K21+K22)*K6 -> 11260.826 | ... AU36: =(+AU21+AU22)*AU6 -> 0 | AV36: =SUM(D36:AU36) -> 432459.14
B37: 401K Contribution-Husband | D37: =(+D23+D24)*D6 -> 17175 | E37: =(+E23+E24)*E6 -> 17100 | F37: =(+F23+F24)*F6 -> 17559.375 | G37: =(+G23+G24)*G6 -> 18028.359 | H37: =(+H23+H24)*H6 -> 16559.068 | I37: =(+I23+I24)*I6 -> 16973.006 | J37: =(+J23+J24)*J6 -> 19495.401 | K37: =(+K23+K24)*K6 -> 20005.286 | ... AU37: =(+AU23+AU24)*AU6 -> 0 | AV37: =SUM(D37:AU37) -> 467827.56
B38: Roth IRA | D38: 3000 | E38: 4000 | F38: 4000 | G38: 4000 | H38: 4000 | I38: 0 | J38: 0 | K38: 0 | L38: 0 | M38: 0 | N38: 0 | O38: 0 | P38: 0 | Q38: 0 | R38: 0 | AB38: 2000 | AC38: 2000 | AD38: 2000 | AE38: 2000 | AF38: 2000 | AG38: 2000 | AV38: =SUM(D38:AU38) -> 31000
B39: Traditional IRA | J39: 4000 | K39: 4000 | L39: 4000 | M39: 4000 | N39: 4000 | O39: 4000 | P39: 4000 | Q39: 4000 | R39: 4000 | S39: 4000 | T39: 4000 | U39: 4000 | V39: 4000 | W39: 4000 | X39: 4000 | Y39: 4000 | Z39: 4000 | AA39: 2000 | AV39: =SUM(D39:AU39) -> 70000
B40: Husband-Child Support | D40: 10000 | E40: 5000 | F40: 0 | G40: 0 | H40: 0 | I40: 0 | J40: 0 | K40: 0 | L40: 0 | M40: 0 | N40: 0 | O40: 0 | P40: 0 | Q40: 0 | R40: 0 | S40: 0 | T40: 0 | U40: 0 | V40: 0 | W40: 0 | X40: 0 | Y40: 0 | Z40: 0 | AA40: 0 | AB40: 0 | AC40: 0 | AD40: 0 | AE40: 0 | AF40: 0 | AG40: 0 | AH40: 0 | AI40: 0 | AJ40: 0 | AK40: 0 | AL40: 0 | AM40: 0 | AN40: 0 | AO40: 0 | AP40: 0 | AQ40: 0 | AR40: 0 | AS40: 0 | AT40: 0 | AU40: 0 | AV40: =SUM(D40:AU40) -> 15000
B41: Mortgage (See Mortgage Sch Tab) | D41: =-Mortgage!$F$1 -> 10953.002 | E41: =-Mortgage!$F$1 -> 10953.002 | F41: =-Mortgage!$F$1 -> 10953.002 | G41: =-Mortgage!$F$1 -> 10953.002 | H41: =-Mortgage!$F$1 -> 10953.002 | I41: =-Mortgage!$F$1 -> 10953.002 | J41: =-Mortgage!$F$1 -> 10953.002 | K41: =-Mortgage!$F$1 -> 10953.002 | ... R41: =-Mortgage!$F$1 -> 10953.002 | AV41: =SUM(D41:AU41) -> 164295.03
B42: Phone/Internet/Electrical | D42: 1000 | E42: =+D42*(1+E$5) -> 1025 | F42: =+E42*(1+F$5) -> 1050.625 | G42: =+F42*(1+G$5) -> 1076.8906 | H42: =+G42*(1+H$5) -> 1103.8129 | I42: =+H42*(1+I$5) -> 1131.4082 | J42: =+I42*(1+J$5) -> 1159.6934 | K42: =+J42*(1+K$5) -> 1188.6858 | L42: =+K42*(1+L$5) -> 1218.4029 | ... AU42: =+AT42*(1+AU$5) -> 2891.5201 | AV42: =SUM(D42:AU42) -> 78552.323
B43: Heating | D43: 1200 | E43: =+D43*(1+E$5) -> 1230 | F43: =+E43*(1+F$5) -> 1260.75 | G43: =+F43*(1+G$5) -> 1292.2687 | H43: =+G43*(1+H$5) -> 1324.5755 | I43: =+H43*(1+I$5) -> 1357.6899 | J43: =+I43*(1+J$5) -> 1391.6321 | K43: =+J43*(1+K$5) -> 1426.4229 | L43: =+K43*(1+L$5) -> 1462.0835 | ... AU43: =+AT43*(1+AU$5) -> 3469.8241 | AV43: =SUM(D43:AU43) -> 94262.788
B44: Car - Gas/Maintenance | D44: 2000 | E44: =+D44*(1+E$5) -> 2050 | F44: =+E44*(1+F$5) -> 2101.25 | G44: =+F44*(1+G$5) -> 2153.7812 | H44: =+G44*(1+H$5) -> 2207.6258 | I44: =+H44*(1+I$5) -> 2262.8164 | J44: =+I44*(1+J$5) -> 2319.3868 | K44: =+J44*(1+K$5) -> 2377.3715 | L44: =+K44*(1+L$5) -> 2436.8058 | ... AU44: =+AT44*(1+AU$5) -> 5783.0402 | AV44: =SUM(D44:AU44) -> 157104.65
B45: Food | D45: 3000 | E45: =+D44*(1+E$5) -> 2050 | F45: =+E44*(1+F$5) -> 2101.25 | G45: =+F44*(1+G$5) -> 2153.7812 | H45: =+G44*(1+H$5) -> 2207.6258 | I45: =+H44*(1+I$5) -> 2262.8164 | J45: =+I44*(1+J$5) -> 2319.3868 | K45: =+J44*(1+K$5) -> 2377.3715 | L45: =+K44*(1+L$5) -> 2436.8058 | ... Q45: =+P44*(1+Q$5) -> 2757.0221 | R45: 5000 | S45: =+R44*(1+S$5) -> 2896.5963 | T45: =+S44*(1+T$5) -> 2969.0112 | U45: =+T44*(1+U$5) -> 3043.2365 | V45: =+U44*(1+V$5) -> 3119.3174 | W45: 6250 | X45: =+W44*(1+X$5) -> 3277.2329 | Y45: =+X44*(1+Y$5) -> 3359.1637 | Z45: =+Y44*(1+Z$5) -> 3443.1428 | AA45: =+Z44*(1+AA$5) -> 3529.2214 | AB45: 7500 | AC45: =+AB44*(1+AC$5) -> 3707.8882 | AD45: =+AC44*(1+AD$5) -> 3800.5854 | AE45: =+AD44*(1+AE$5) -> 3895.6 | AF45: =+AE44*(1+AF$5) -> 3992.99 | AG45: =+AF44*(1+AG$5) -> 4092.8148 | AH45: =+AG44*(1+AH$5) -> 4195.1352 | AI45: =+AH44*(1+AI$5) -> 4300.0135 | AJ45: =+AI44*(1+AJ$5) -> 4407.5139 | ... AU45: =+AT44*(1+AU$5) -> 5783.0402 | AV45: =SUM(D44:AU44) -> 157104.65
B46: Insurance - Car/House/Life | D46: 1550 | E46: =+D46*(1+E$5) -> 1588.75 | F46: =+E46*(1+F$5) -> 1628.4687 | G46: =+F46*(1+G$5) -> 1669.1805 | H46: =+G46*(1+H$5) -> 1710.91 | I46: =+H46*(1+I$5) -> 1753.6827 | J46: =+I46*(1+J$5) -> 1797.5248 | K46: =+J46*(1+K$5) -> 1842.4629 | L46: =+K46*(1+L$5) -> 1888.5245 | ... AU46: =+AT46*(1+AU$5) -> 4481.8561 | AV46: =SUM(D46:AU46) -> 121756.1
B47: Insurance- Health & Dental | D47: 1000 | E47: 1800 | F47: 1800 | G47: 1800 | H47: 2000 | I47: 2000 | J47: 2100 | K47: 2100 | L47: 2200 | M47: 2200 | N47: 2300 | O47: 2300 | P47: 2400 | Q47: 2400 | R47: 2500 | S47: 2500 | T47: 2600 | U47: 2600 | V47: 2700 | W47: 2700 | X47: 2800 | Y47: 2800 | Z47: 2800 | AA47: 2800 | AB47: 3000 | AC47: 3100 | AD47: 3100 | AE47: 3200 | AF47: 3200 | AG47: 3300 | AH47: 4000 | AI47: 4000 | AJ47: 4200 | AK47: 4200 | AL47: 4300 | AM47: 4300 | AN47: 4400 | AO47: 4400 | AP47: 4500 | AQ47: 4500 | AR47: 4600 | AS47: 4600 | AT47: 4700 | AU47: 4700 | AV47: =SUM(D47:AU47) -> 135500
B48: Healthcare (Co-Pay) | D48: 1000 | E48: =+D48*(1+E$5) -> 1025 | F48: =+E48*(1+F$5) -> 1050.625 | G48: =+F48*(1+G$5) -> 1076.8906 | H48: =+G48*(1+H$5) -> 1103.8129 | I48: =+H48*(1+I$5) -> 1131.4082 | J48: =+I48*(1+J$5) -> 1159.6934 | K48: =+J48*(1+K$5) -> 1188.6858 | L48: =+K48*(1+L$5) -> 1218.4029 | ... AF48: =+AE48*(1+AF$5) -> 1996.495 | AG48: 4000 | AH48: =+AG48*(1+AH$5) -> 4100 | AI48: =+AH48*(1+AI$5) -> 4202.5 | AJ48: =+AI48*(1+AJ$5) -> 4307.5625 | AK48: =+AJ48*(1+AK$5) -> 4415.2516 | AL48: =+AK48*(1+AL$5) -> 4525.6329 | AM48: =+AL48*(1+AM$5) -> 4638.7737 | AN48: =+AM48*(1+AN$5) -> 4754.743 | AO48: =+AN48*(1+AO$5) -> 4873.6116 | ... AU48: =+AT48*(1+AU$5) -> 5651.8953 | AV48: =SUM(D48:AU48) -> 113584
B49: Entertainment | D49: 1800 | E49: =+D49*(1+E$5) -> 1845 | F49: =+E49*(1+F$5) -> 1891.125 | G49: =+F49*(1+G$5) -> 1938.4031 | H49: =+G49*(1+H$5) -> 1986.8632 | I49: =+H49*(1+I$5) -> 2036.5348 | J49: =+I49*(1+J$5) -> 2087.4482 | K49: =+J49*(1+K$5) -> 2139.6344 | L49: =+K49*(1+L$5) -> 2193.1252 | ... AU49: =+AT49*(1+AU$5) -> 5204.7361 | AV49: =SUM(D49:AU49) -> 141394.18
B50: Vacation/Travel | D50: 3000 | E50: =+D50*(1+E$5) -> 3075 | F50: =+E50*(1+F$5) -> 3151.875 | G50: =+F50*(1+G$5) -> 3230.6719 | H50: =+G50*(1+H$5) -> 3311.4387 | I50: =+H50*(1+I$5) -> 3394.2246 | J50: =+I50*(1+J$5) -> 3479.0803 | K50: =+J50*(1+K$5) -> 3566.0573 | L50: =+K50*(1+L$5) -> 3655.2087 | M50: 5000 | N50: =+M50*(1+N$5) -> 5125 | O50: =+N50*(1+O$5) -> 5253.125 | P50: =+O50*(1+P$5) -> 5384.4531 | Q50: =+P50*(1+Q$5) -> 5519.0645 | R50: 6000 | S50: =+R50*(1+S$5) -> 6150 | T50: =+S50*(1+T$5) -> 6303.75 | U50: =+T50*(1+U$5) -> 6461.3437 | V50: =+U50*(1+V$5) -> 6622.8773 | W50: 10000 | X50: =+W50*(1+X$5) -> 10250 | Y50: =+X50*(1+Y$5) -> 10506.25 | Z50: =+Y50*(1+Z$5) -> 10768.906 | AA50: =+Z50*(1+AA$5) -> 11038.129 | AB50: 15000 | AC50: =+AB50*(1+AC$5) -> 15375 | AD50: =+AC50*(1+AD$5) -> 15759.375 | AE50: =+AD50*(1+AE$5) -> 16153.359 | AF50: =+AE50*(1+AF$5) -> 16557.193 | AG50: 25000 | AH50: =+AG50*(1+AH$5) -> 25625 | AI50: =+AH50*(1+AI$5) -> 26265.625 | AJ50: =+AI50*(1+AJ$5) -> 26922.266 | AK50: =+AJ50*(1+AK$5) -> 27595.322 | AL50: =+AK50*(1+AL$5) -> 28285.205 | AM50: =+AL50*(1+AM$5) -> 28992.335 | AN50: =+AM50*(1+AN$5) -> 29717.144 | AO50: =+AN50*(1+AO$5) -> 30460.072 | ... AU50: =+AT50*(1+AU$5) -> 35324.346 | AV50: =SUM(D50:AU50) -> 667389.55
B51: Clothing | D51: 3600 | E51: =+D51*(1+E$5) -> 3690 | F51: =+E51*(1+F$5) -> 3782.25 | G51: =+F51*(1+G$5) -> 3876.8062 | H51: =+G51*(1+H$5) -> 3973.7264 | I51: =+H51*(1+I$5) -> 4073.0696 | J51: =+I51*(1+J$5) -> 4174.8963 | K51: =+J51*(1+K$5) -> 4279.2687 | L51: =+K51*(1+L$5) -> 4386.2504 | ... Q51: =+P51*(1+Q$5) -> 4962.6398 | R51: 6000 | S51: =+R51*(1+S$5) -> 6150 | T51: =+S51*(1+T$5) -> 6303.75 | U51: =+T51*(1+U$5) -> 6461.3437 | V51: =+U51*(1+V$5) -> 6622.8773 | W51: 7500 | X51: =+W51*(1+X$5) -> 7687.5 | Y51: =+X51*(1+Y$5) -> 7879.6875 | Z51: =+Y51*(1+Z$5) -> 8076.6797 | AA51: =+Z51*(1+AA$5) -> 8278.5967 | AB51: 8000 | AC51: =+AB51*(1+AC$5) -> 8200 | AD51: =+AC51*(1+AD$5) -> 8405 | AE51: =+AD51*(1+AE$5) -> 8615.125 | AF51: =+AE51*(1+AF$5) -> 8830.5031 | AG51: =+AF51*(1+AG$5) -> 9051.2657 | AH51: =+AG51*(1+AH$5) -> 9277.5473 | AI51: =+AH51*(1+AI$5) -> 9509.486 | AJ51: =+AI51*(1+AJ$5) -> 9747.2232 | ... AU51: =+AT51*(1+AU$5) -> 12789.201 | AV51: =SUM(D51:AU51) -> 334785.93
B52: Home Improvements | D52: 4000 | E52: 10000 | F52: 10000 | G52: 5000 | H52: 5000 | I52: 5000 | J52: 10000 | K52: 5000 | L52: 5000 | M52: 5000 | N52: 5000 | O52: 10000 | P52: 5000 | Q52: 5000 | R52: 5000 | S52: 5000 | T52: 10000 | U52: 5000 | V52: 5000 | W52: 5000 | X52: 5000 | Y52: 10000 | Z52: 5000 | AA52: 5000 | AB52: 5000 | AC52: 5000 | AD52: 10000 | AE52: 5000 | AF52: 5000 | AG52: 5000 | AH52: 5000 | AI52: 5000 | AJ52: 10000 | AK52: 5000 | AL52: 5000 | AM52: 5000 | AN52: 5000 | AO52: 5000 | AP52: 10000 | AQ52: 5000 | AR52: 5000 | AS52: 5000 | AT52: 5000 | AU52: 5000 | AV52: =SUM(D52:AU52) -> 264000
B53: Miscellaneous | D53: 2500 | E53: =+D53*(1+E$5) -> 2562.5 | F53: =+E53*(1+F$5) -> 2626.5625 | G53: =+F53*(1+G$5) -> 2692.2266 | H53: =+G53*(1+H$5) -> 2759.5322 | I53: =+H53*(1+I$5) -> 2828.5205 | J53: =+I53*(1+J$5) -> 2899.2335 | K53: =+J53*(1+K$5) -> 2971.7144 | L53: =+K53*(1+L$5) -> 3046.0072 | ... Q53: =+P53*(1+Q$5) -> 3446.2776 | R53: 6000 | S53: =+R53*(1+S$5) -> 6150 | T53: =+S53*(1+T$5) -> 6303.75 | U53: =+T53*(1+U$5) -> 6461.3437 | V53: =+U53*(1+V$5) -> 6622.8773 | W53: 7500 | X53: =+W53*(1+X$5) -> 7687.5 | Y53: =+X53*(1+Y$5) -> 7879.6875 | Z53: =+Y53*(1+Z$5) -> 8076.6797 | AA53: =+Z53*(1+AA$5) -> 8278.5967 | AB53: 8000 | AC53: =+AB53*(1+AC$5) -> 8200 | AD53: =+AC53*(1+AD$5) -> 8405 | AE53: =+AD53*(1+AE$5) -> 8615.125 | AF53: =+AE53*(1+AF$5) -> 8830.5031 | AG53: =+AF53*(1+AG$5) -> 9051.2657 | AH53: =+AG53*(1+AH$5) -> 9277.5473 | AI53: =+AH53*(1+AI$5) -> 9509.486 | AJ53: =+AI53*(1+AJ$5) -> 9747.2232 | ... AU53: =+AT53*(1+AU$5) -> 12789.201 | AV53: =SUM(D53:AU53) -> 316615.08
B54: Charity/Gifts | AH54: 50000 | AI54: 50000 | AJ54: 50000 | AK54: 100000 | AL54: 100000 | AM54: 100000 | AN54: 100000 | AO54: 100000 | AP54: 115000 | AQ54: 120000 | AR54: 135000 | AS54: 150000 | AT54: 165000 | AU54: 170000
B56: Total Annual Expenses | D56: =SUM(D34:D54) -> 125008 | E56: =SUM(E34:E54) -> 168570 | F56: =SUM(F34:F54) -> 167142.38 | G56: =SUM(G34:G54) -> 166357.15 | H56: =SUM(H34:H54) -> 165567.96 | I56: =SUM(I34:I54) -> 162362.41 | J56: =SUM(J34:J54) -> 181448.64 | K56: =SUM(K34:K54) -> 184765.96 | ... AU56: =SUM(AU34:AU54) -> 478570.95 | AV56: =SUM(D56:AU56) -> 9676925.3
B58: Income Surplus/Deficit | D58: =+D31-D56 -> 45491.998 | E58: =+E31-E56 -> 5179.9982 | F58: =+F31-F56 -> 11980.117 | G58: =+G31-G56 -> 18294.314 | H58: =+H31-H56 -> 11786.724 | I58: =+I31-I56 -> 20350.298 | J58: =+J31-J56 -> 20782.405 | K58: =+K31-K56 -> 23674.791 | ... AU58: =+AU31-AU56 -> -52430.95 | AV58: =SUM(D58:AU58) -> -294458.29
B59: Balance Sheet | AU59: FV
AU60: Property
B61: House | C61: 100000 | D61: =+Mortgage!C17 -> 96499.3 | E61: =+Mortgage!C30 -> 92051.759 | F61: =+Mortgage!C42 -> 87625.548 | G61: =+Mortgage!C54 -> 82867.651 | H61: =+Mortgage!C66 -> 77753.212 | I61: =+Mortgage!C77 -> 72728.979 | J61: =Mortgage!C80 -> 71299.981 | K61: =Mortgage!C102 -> 59993.297 | L61: =+Mortgage!C114 -> 53164.724 | M61: =+Mortgage!C126 -> 45824.438 | N61: =+Mortgage!C137 -> 38613.618 | O61: =+Mortgage!C150 -> 29452.472 | P61: =+Mortgage!C162 -> 20335.263 | Q61: =+Mortgage!C174 -> 10534.838 | R61: =+Mortgage!C186 -> 4.3883119e-11 | AU61: =250000*11.467 -> 2866750 | AV61: FV table 50 years, 5%
B62: 46 Acres | AU62: =100000*11.467 -> 1146700 | AV62: FV table 50 years, 5%
B63: Joint Savings/CD | C63: 20000 | D63: =+C63-D70-D71-D71+D58 -> 49491.998 | E63: =+D63-E70-E71-E71+E58 -> 54671.996 | F63: =+E63-F70-F71-F71+F58 -> 66652.113 | G63: =+F63-G70-G71-G71+G58 -> 54946.428 | H63: =+G63-H70-H71-H71+H58 -> 66733.152 | I63: =+H63-I70-I71-I71+I58 -> 87083.45 | J63: =+I63-J70-J71-J71+J58 -> 107865.85 | K63: =+J63-K70-K71-K71+K58 -> 131540.65 | ... AU63: =+AT63-AU70-AU71-AU71+AU58 -> -620458.29
B64: 401K-Wife | C64: 58000 | D64: =+(C64*(1+D8))+D36 -> 71040 | E64: =+(D64*(1+E8))+E36 -> 85685.7 | F64: =+(E64*(1+F8))+F36 -> 101849.56 | G64: =+(F64*(1+G8))+G36 -> 119666.88 | H64: =+(G64*(1+H8))+H36 -> 139284.37 | I64: =+(H64*(1+I8))+I36 -> 160861.01 | J64: =+(I64*(1+J8))+J36 -> 184569.15 | K64: =+(J64*(1+K8))+K36 -> 210595.51 | ... AS64: =+(AR64*(1+AS8))+AS36 -> 4959198.9 | AT64: =(+AS64*(1+AT8)+AT36)-AT27 -> 4955934.8 | AU64: =(+AT64*(1+AU8)+AU36)-AU27 -> 4942409.6
B65: 401K-Husband | C65: 72000 | D65: =+C65*(1+D9)+D37 -> 94935 | E65: =+D65*(1+E9)+E37 -> 119629.8 | F65: =+E65*(1+F9)+F37 -> 146759.56 | G65: =+F65*(1+G9)+G37 -> 176528.68 | H65: =+G65*(1+H9)+H37 -> 207210.05 | I65: =+H65*(1+I9)+I37 -> 240759.86 | J65: =+I65*(1+J9)+J37 -> 279516.05 | K65: =+J65*(1+K9)+K37 -> 321882.62 | ... AG65: =+AF65*(1+AG9)+AG37 -> 2043785.4 | AH65: =(+AG65*(1+AH9)+AH37)-AH27 -> 2086412.6 | AI65: =(+AH65*(1+AI9)+AI37)-AI27 -> 2131597.3 | AJ65: =(+AI65*(1+AJ9)+AJ37)-AJ27 -> 2179493.2 | AK65: =(+AJ65*(1+AK9)+AK37)-AK27 -> 2160262.7 | AL65: =(+AK65*(1+AL9)+AL37)-AL27 -> 2139878.5 | AM65: =(+AL65*(1+AM9)+AM37)-AM27 -> 2118271.2 | AN65: =(+AM65*(1+AN9)+AN37)-AN27 -> 2095367.5 | AO65: =(+AN65*(1+AO9)+AO37)-AO27 -> 2051089.5 | ... AS65: =(+AR65*(1+AS9)+AS37)-AS27 -> 2291691.2 | AT65: =(+AS65*(1+AT9)+AT37) -> 2429192.6 | AU65: =(+AT65*(1+AU9)+AU37)-AU27 -> 2164944.2
B66: Roth IRA | C66: 4000 | D66: =(+C66*(1+D10))+D38 -> 7320 | E66: =(+D66*(1+E10))+E38 -> 11905.6 | F66: =(+E66*(1+F10))+F38 -> 16858.048 | G66: =(+F66*(1+G10))+G38 -> 22206.692 | H66: =(+G66*(1+H10))+H38 -> 27983.227 | I66: =(+H66*(1+I10))+I38 -> 30221.885 | J66: =(+I66*(1+J10))+J38 -> 32639.636 | K66: =(+J66*(1+K10))+K38 -> 35250.807 | ... AA66: =(+Z66*(1+AA10))+AA38 -> 98322.375 | AB66: =((+AA66*(1+AB10))+AB38)-AB29 -> 106221.72 | AC66: =((+AB66*(1+AC10))+AC38)-AC29 -> 114595.02 | AD66: =((+AC66*(1+AD10))+AD38)-AD29 -> 123470.72 | AE66: =((+AD66*(1+AE10))+AE38)-AE29 -> 132878.97 | AF66: =((+AE66*(1+AF10))+AF38)-AF29 -> 142851.7 | AG66: =((+AF66*(1+AG10))+AG38)-AG29 -> 143422.81 | AH66: =((+AG66*(1+AH10))+AH38)-AH29 -> 102028.17 | AI66: =((+AH66*(1+AI10))+AI38)-AI29 -> 58149.864 | ... AK66: =((+AJ66*(1+AK10))+AK38)-AK29 -> -27767.713
B67: Traditional IRA | C67: 0 | D67: =(+C67*(1+D11))+D39 -> 0 | E67: =(+D67*(1+E11))+E39 -> 0 | F67: =(+E67*(1+F11))+F39 -> 0 | G67: =(+F67*(1+G11))+G39 -> 0 | H67: =(+G67*(1+H11))+H39 -> 0 | I67: =(+H67*(1+I11))+I39 -> 0 | J67: =(+I67*(1+J11))+J39 -> 4000 | K67: =(+J67*(1+K11))+K39 -> 8320 | ... AG67: =(+AF67*(1+AG11))+AG39 -> 178221.53 | AH67: =((+AG67*(1+AH11))+AH39)-AH28 -> 173914.83 | AI67: =((+AH67*(1+AI11))+AI39)-AI28 -> 164349.72 | AJ67: =((+AI67*(1+AJ11))+AJ39)-AJ28 -> 154210.7 | AK67: =((+AJ67*(1+AK11))+AK39)-AK28 -> 158463.34 | AL67: =((+AK67*(1+AL11))+AL39)-AL28 -> 132971.14 | AM67: =((+AL67*(1+AM11))+AM39)-AM28 -> 100949.41 | AN67: =((+AM67*(1+AN11))+AN39)-AN28 -> 42006.375 | AO67: =((+AN67*(1+AO11))+AO39)-AO28 -> -3756.2422
B68: Inheritence (In 2004 and 2016) | G68: 7500 | H68: =+G68*1.08 -> 8100 | I68: =+H68*1.08 -> 8748 | J68: =+I68*1.08 -> 9447.84 | K68: =+J68*1.08 -> 10203.667 | L68: =+K68*1.08 -> 11019.961 | M68: =+L68*1.08 -> 11901.557 | N68: =+M68*1.08 -> 12853.682 | O68: =+N68*1.08 -> 13881.977 | ... R68: =+Q68*1.08 -> 17487.292 | S68: =(+R68*1.08)+20000 -> 38886.276 | T68: =+S68*1.08 -> 41997.178 | U68: =+T68*1.08 -> 45356.952 | V68: =+U68*1.08 -> 48985.508 | W68: =+V68*1.08 -> 52904.349 | X68: =+W68*1.08 -> 57136.697 | Y68: =+X68*1.08 -> 61707.633 | Z68: =+Y68*1.08 -> 66644.243 | AA68: =+Z68*1.08 -> 71975.783 | ... AU68: =+AT68*1.08 -> 335476.04
B69: Auto Accident Settlement | E69: 45000 | F69: =+E69*(1+0.08) -> 48600 | G69: =+F69*(1+0.08) -> 52488 | H69: =+G69*(1+0.08) -> 56687.04 | I69: =+H69*(1+0.08) -> 61222.003 | J69: =+I69*(1+0.08) -> 66119.763 | K69: =+J69*(1+0.08) -> 71409.345 | L69: =+K69*(1+0.08) -> 77122.092 | M69: =+L69*(1+0.08) -> 83291.859 | ... AU69: =+AT69*(1+0.08) -> 1140276.7
B70: Car/Truck Purchase (Includes trade-in) | G70: 30000 | N70: 35000 | U70: 35000 | AA70: 40000 | AB70: 40000 | AH70: 50000 | AI70: 50000 | AP70: 50000
B71: Tractor Purchase | D71: =+C63-12000 -> 8000
AU74: =SUM(AU63:AU69) -> 7962648.3 | AV74: Cash

Sheet Mortgage
A1: Mortgage Payment Schedule | D1: Mth/Pay | E1: =PMT(0.00604,180,100000,0,0) -> -912.75015 | F1: =+E1*12 -> -10953.002 | G1: Annual/Pay
E2: =+E1*180 -> -164295.03 | F2: Cost of loan
E3: =+E2+C6 -> -64295.026 | F3: Interest on loan
C4: Mortgage | E4: Principal
A5: Payment | B5: PPMT | C5: Balance | D5: End of Yr | E5: Paid
C6: 100000
A7: 1 | B7: =PPMT(0.00604,A7,180,100000,0) -> -308.75015 | C7: =+C6+B7 -> 99691.25
A8: =+A7+1 -> 2 | B8: =PPMT(0.00604,A8,180,100000,0) -> -310.615 | C8: =+C7+B8 -> 99380.635
A9: =+A8+1 -> 3 | B9: =PPMT(0.00604,A9,180,100000,0) -> -312.49111 | C9: =+C8+B9 -> 99068.144
A10: =+A9+1 -> 4 | B10: =PPMT(0.00604,A10,180,100000,0) -> -314.37856 | C10: =+C9+B10 -> 98753.765
A11: =+A10+1 -> 5 | B11: =PPMT(0.00604,A11,180,100000,0) -> -316.27741 | C11: =+C10+B11 -> 98437.488
A12: =+A11+1 -> 6 | B12: =PPMT(0.00604,A12,180,100000,0) -> -318.18772 | C12: =+C11+B12 -> 98119.3
A13: =+A12+1 -> 7 | B13: =PPMT(0.00604,A13,180,100000,0) -> -320.10957 | C13: =+C12+B13 -> 97799.19
A14: =+A13+1 -> 8 | B14: =PPMT(0.00604,A14,180,100000,0) -> -322.04304 | C14: =+C13+B14 -> 97477.147
A15: =+A14+1 -> 9 | B15: =PPMT(0.00604,A15,180,100000,0) -> -323.98818 | C15: =+C14+B15 -> 97153.159
A16: =+A15+1 -> 10 | B16: =PPMT(0.00604,A16,180,100000,0) -> -325.94507 | C16: =+C15+B16 -> 96827.214
A17: =+A16+1 -> 11 | B17: =PPMT(0.00604,A17,180,100000,0) -> -327.91377 | C17: =+C16+B17 -> 96499.3
A18: =+A17+1 -> 12 | B18: =PPMT(0.00604,A18,180,100000,0) -> -329.89437 | C18: =+C17+B18 -> 96169.406 | D18: 2025 | E18: =+C6-C18 -> 3830.5939 | F18: =SUM(B7:B18) -> -3830.5939 | G18: =+E18+F18 -> -7.2759576e-12
A19: =+A18+1 -> 13 | B19: =PPMT(0.00604,A19,180,100000,0) -> -331.88693 | C19: =+C18+B19 -> 95837.519
A20: =+A19+1 -> 14 | B20: =PPMT(0.00604,A20,180,100000,0) -> -333.89153 | C20: =+C19+B20 -> 95503.628
A21: =+A20+1 -> 15 | B21: =PPMT(0.00604,A21,180,100000,0) -> -335.90824 | C21: =+C20+B21 -> 95167.719
A22: =+A21+1 -> 16 | B22: =PPMT(0.00604,A22,180,100000,0) -> -337.93712 | C22: =+C21+B22 -> 94829.782
A23: =+A22+1 -> 17 | B23: =PPMT(0.00604,A23,180,100000,0) -> -339.97826 | C23: =+C22+B23 -> 94489.804
A24: =+A23+1 -> 18 | B24: =PPMT(0.00604,A24,180,100000,0) -> -342.03173 | C24: =+C23+B24 -> 94147.772
A25: =+A24+1 -> 19 | B25: =PPMT(0.00604,A25,180,100000,0) -> -344.0976 | C25: =+C24+B25 -> 93803.675
A26: =+A25+1 -> 20 | B26: =PPMT(0.00604,A26,180,100000,0) -> -346.17595 | C26: =+C25+B26 -> 93457.499
A27: =+A26+1 -> 21 | B27: =PPMT(0.00604,A27,180,100000,0) -> -348.26686 | C27: =+C26+B27 -> 93109.232
A28: =+A27+1 -> 22 | B28: =PPMT(0.00604,A28,180,100000,0) -> -350.37039 | C28: =+C27+B28 -> 92758.861
A29: =+A28+1 -> 23 | B29: =PPMT(0.00604,A29,180,100000,0) -> -352.48662 | C29: =+C28+B29 -> 92406.375
A30: =+A29+1 -> 24 | B30: =PPMT(0.00604,A30,180,100000,0) -> -354.61564 | C30: =+C29+B30 -> 92051.759 | D30: =+D18+1 -> 2026 | E30: =+C18-C30 -> 4117.6469 | F30: =SUM(B19:B30) -> -4117.6469 | G30: =+E30+F30 -> 0
A31: =+A30+1 -> 25 | B31: =PPMT(0.00604,A31,180,100000,0) -> -356.75752 | C31: =+C30+B31 -> 91695.002
A32: =+A31+1 -> 26 | B32: =PPMT(0.00604,A32,180,100000,0) -> -358.91234 | C32: =+C31+B32 -> 91336.089
A33: =+A32+1 -> 27 | B33: =PPMT(0.00604,A33,180,100000,0) -> -361.08017 | C33: =+C32+B33 -> 90975.009
A34: =+A33+1 -> 28 | B34: =PPMT(0.00604,A34,180,100000,0) -> -363.26109 | C34: =+C33+B34 -> 90611.748
A35: =+A34+1 -> 29 | B35: =PPMT(0.00604,A35,180,100000,0) -> -365.45519 | C35: =+C34+B35 -> 90246.293
A36: =+A35+1 -> 30 | B36: =PPMT(0.00604,A36,180,100000,0) -> -367.66254 | C36: =+C35+B36 -> 89878.63
A37: =+A36+1 -> 31 | B37: =PPMT(0.00604,A37,180,100000,0) -> -369.88322 | C37: =+C36+B37 -> 89508.747
A38: =+A37+1 -> 32 | B38: =PPMT(0.00604,A38,180,100000,0) -> -372.11731 | C38: =+C37+B38 -> 89136.63
A39: =+A38+1 -> 33 | B39: =PPMT(0.00604,A39,180,100000,0) -> -374.3649 | C39: =+C38+B39 -> 88762.265
A40: =+A39+1 -> 34 | B40: =PPMT(0.00604,A40,180,100000,0) -> -376.62607 | C40: =+C39+B40 -> 88385.639
A41: =+A40+1 -> 35 | B41: =PPMT(0.00604,A41,180,100000,0) -> -378.90089 | C41: =+C40+B41 -> 88006.738
A42: =+A41+1 -> 36 | B42: =PPMT(0.00604,A42,180,100000,0) -> -381.18945 | C42: =+C41+B42 -> 87625.548 | D42: =+D30+1 -> 2027 | E42: =+C30-C42 -> 4426.2107 | F42: =SUM(B31:B42) -> -4426.2107 | G42: =+E42+F42 -> 1.2732926e-11
A43: =+A42+1 -> 37 | B43: =PPMT(0.00604,A43,180,100000,0) -> -383.49183 | C43: =+C42+B43 -> 87242.057
A44: =+A43+1 -> 38 | B44: =PPMT(0.00604,A44,180,100000,0) -> -385.80812 | C44: =+C43+B44 -> 86856.249
A45: =+A44+1 -> 39 | B45: =PPMT(0.00604,A45,180,100000,0) -> -388.13841 | C45: =+C44+B45 -> 86468.11
A46: =+A45+1 -> 40 | B46: =PPMT(0.00604,A46,180,100000,0) -> -390.48276 | C46: =+C45+B46 -> 86077.627
A47: =+A46+1 -> 41 | B47: =PPMT(0.00604,A47,180,100000,0) -> -392.84128 | C47: =+C46+B47 -> 85684.786
A48: =+A47+1 -> 42 | B48: =PPMT(0.00604,A48,180,100000,0) -> -395.21404 | C48: =+C47+B48 -> 85289.572
A49: =+A48+1 -> 43 | B49: =PPMT(0.00604,A49,180,100000,0) -> -397.60113 | C49: =+C48+B49 -> 84891.971
A50: =+A49+1 -> 44 | B50: =PPMT(0.00604,A50,180,100000,0) -> -400.00264 | C50: =+C49+B50 -> 84491.968
A51: =+A50+1 -> 45 | B51: =PPMT(0.00604,A51,180,100000,0) -> -402.41866 | C51: =+C50+B51 -> 84089.55
A52: =+A51+1 -> 46 | B52: =PPMT(0.00604,A52,180,100000,0) -> -404.84927 | C52: =+C51+B52 -> 83684.7
A53: =+A52+1 -> 47 | B53: =PPMT(0.00604,A53,180,100000,0) -> -407.29456 | C53: =+C52+B53 -> 83277.406
A54: =+A53+1 -> 48 | B54: =PPMT(0.00604,A54,180,100000,0) -> -409.75462 | C54: =+C53+B54 -> 82867.651 | D54: =+D42+1 -> 2028 | E54: =+C42-C54 -> 4757.8973 | F54: =SUM(B43:B54) -> -4757.8973 | G54: =+E54+F54 -> 0
A55: =+A54+1 -> 49 | B55: =PPMT(0.00604,A55,180,100000,0) -> -412.22953 | C55: =+C54+B55 -> 82455.422
A56: =+A55+1 -> 50 | B56: =PPMT(0.00604,A56,180,100000,0) -> -414.7194 | C56: =+C55+B56 -> 82040.702
A57: =+A56+1 -> 51 | B57: =PPMT(0.00604,A57,180,100000,0) -> -417.22431 | C57: =+C56+B57 -> 81623.478
A58: =+A57+1 -> 52 | B58: =PPMT(0.00604,A58,180,100000,0) -> -419.74434 | C58: =+C57+B58 -> 81203.734
A59: =+A58+1 -> 53 | B59: =PPMT(0.00604,A59,180,100000,0) -> -422.2796 | C59: =+C58+B59 -> 80781.454
A60: =+A59+1 -> 54 | B60: =PPMT(0.00604,A60,180,100000,0) -> -424.83016 | C60: =+C59+B60 -> 80356.624
A61: =+A60+1 -> 55 | B61: =PPMT(0.00604,A61,180,100000,0) -> -427.39614 | C61: =+C60+B61 -> 79929.228
A62: =+A61+1 -> 56 | B62: =PPMT(0.00604,A62,180,100000,0) -> -429.97761 | C62: =+C61+B62 -> 79499.25
A63: =+A62+1 -> 57 | B63: =PPMT(0.00604,A63,180,100000,0) -> -432.57468 | C63: =+C62+B63 -> 79066.675
A64: =+A63+1 -> 58 | B64: =PPMT(0.00604,A64,180,100000,0) -> -435.18743 | C64: =+C63+B64 -> 78631.488
A65: =+A64+1 -> 59 | B65: =PPMT(0.00604,A65,180,100000,0) -> -437.81596 | C65: =+C64+B65 -> 78193.672
A66: =+A65+1 -> 60 | B66: =PPMT(0.00604,A66,180,100000,0) -> -440.46037 | C66: =+C65+B66 -> 77753.212 | D66: =+D54+1 -> 2029 | E66: =+C54-C66 -> 5114.4395 | F66: =SUM(B55:B66) -> -5114.4395 | G66: =+E66+F66 -> 0
A67: =+A66+1 -> 61 | B67: =PPMT(0.00604,A67,180,100000,0) -> -443.12075 | C67: =+C66+B67 -> 77310.091
A68: =+A67+1 -> 62 | B68: =PPMT(0.00604,A68,180,100000,0) -> -445.7972 | C68: =+C67+B68 -> 76864.294
A69: =+A68+1 -> 63 | B69: =PPMT(0.00604,A69,180,100000,0) -> -448.48981 | C69: =+C68+B69 -> 76415.804
A70: =+A69+1 -> 64 | B70: =PPMT(0.00604,A70,180,100000,0) -> -451.19869 | C70: =+C69+B70 -> 75964.605
A71: =+A70+1 -> 65 | B71: =PPMT(0.00604,A71,180,100000,0) -> -453.92393 | C71: =+C70+B71 -> 75510.681
A72: =+A71+1 -> 66 | B72: =PPMT(0.00604,A72,180,100000,0) -> -456.66563 | C72: =+C71+B72 -> 75054.016
A73: =+A72+1 -> 67 | B73: =PPMT(0.00604,A73,180,100000,0) -> -459.42389 | C73: =+C72+B73 -> 74594.592
A74: =+A73+1 -> 68 | B74: =PPMT(0.00604,A74,180,100000,0) -> -462.19881 | C74: =+C73+B74 -> 74132.393
A75: =+A74+1 -> 69 | B75: =PPMT(0.00604,A75,180,100000,0) -> -464.99049 | C75: =+C74+B75 -> 73667.402
A76: =+A75+1 -> 70 | B76: =PPMT(0.00604,A76,180,100000,0) -> -467.79904 | C76: =+C75+B76 -> 73199.603
A77: =+A76+1 -> 71 | B77: =PPMT(0.00604,A77,180,100000,0) -> -470.62454 | C77: =+C76+B77 -> 72728.979
A78: =+A77+1 -> 72 | B78: =PPMT(0.00604,A78,180,100000,0) -> -473.46711 | C78: =+C77+B78 -> 72255.512 | D78: =+D66+1 -> 2030 | E78: =+C66-C78 -> 5497.6999 | F78: =SUM(B67:B78) -> -5497.6999 | G78: =+E78+F78 -> -1.4551915e-11
A79: =+A78+1 -> 73 | B79: =PPMT(0.00604,A79,180,100000,0) -> -476.32686 | C79: =+C78+B79 -> 71779.185
A80: =+A79+1 -> 74 | B80: =PPMT(0.00604,A80,180,100000,0) -> -479.20387 | C80: =+C79+B80 -> 71299.981
A81: =+A80+1 -> 75 | B81: =PPMT(0.00604,A81,180,100000,0) -> -482.09826 | C81: =+C80+B81 -> 70817.883
A82: =+A81+1 -> 76 | B82: =PPMT(0.00604,A82,180,100000,0) -> -485.01014 | C82: =+C81+B82 -> 70332.873
A83: =+A82+1 -> 77 | B83: =PPMT(0.00604,A83,180,100000,0) -> -487.9396 | C83: =+C82+B83 -> 69844.933
A84: =+A83+1 -> 78 | B84: =PPMT(0.00604,A84,180,100000,0) -> -490.88675 | C84: =+C83+B84 -> 69354.046
A85: =+A84+1 -> 79 | B85: =PPMT(0.00604,A85,180,100000,0) -> -493.85171 | C85: =+C84+B85 -> 68860.195
A86: =+A85+1 -> 80 | B86: =PPMT(0.00604,A86,180,100000,0) -> -496.83457 | C86: =+C85+B86 -> 68363.36
A87: =+A86+1 -> 81 | B87: =PPMT(0.00604,A87,180,100000,0) -> -499.83545 | C87: =+C86+B87 -> 67863.525
A88: =+A87+1 -> 82 | B88: =PPMT(0.00604,A88,180,100000,0) -> -502.85446 | C88: =+C87+B88 -> 67360.67
A89: =+A88+1 -> 83 | B89: =PPMT(0.00604,A89,180,100000,0) -> -505.8917 | C89: =+C88+B89 -> 66854.778
A90: =+A89+1 -> 84 | B90: =PPMT(0.00604,A90,180,100000,0) -> -508.94729 | C90: =+C89+B90 -> 66345.831 | D90: =+D78+1 -> 2031 | E90: =+C78-C90 -> 5909.6806 | F90: =SUM(B79:B90) -> -5909.6806 | G90: =+E90+F90 -> 0
A91: =+A90+1 -> 85 | B91: =PPMT(0.00604,A91,180,100000,0) -> -512.02133 | C91: =+C90+B91 -> 65833.81
A92: =+A91+1 -> 86 | B92: =PPMT(0.00604,A92,180,100000,0) -> -515.11394 | C92: =+C91+B92 -> 65318.696
A93: =+A92+1 -> 87 | B93: =PPMT(0.00604,A93,180,100000,0) -> -518.22522 | C93: =+C92+B93 -> 64800.471
A94: =+A93+1 -> 88 | B94: =PPMT(0.00604,A94,180,100000,0) -> -521.3553 | C94: =+C93+B94 -> 64279.115
A95: =+A94+1 -> 89 | B95: =PPMT(0.00604,A95,180,100000,0) -> -524.50429 | C95: =+C94+B95 -> 63754.611
A96: =+A95+1 -> 90 | B96: =PPMT(0.00604,A96,180,100000,0) -> -527.6723 | C96: =+C95+B96 -> 63226.939
A97: =+A96+1 -> 91 | B97: =PPMT(0.00604,A97,180,100000,0) -> -530.85944 | C97: =+C96+B97 -> 62696.079
A98: =+A97+1 -> 92 | B98: =PPMT(0.00604,A98,180,100000,0) -> -534.06583 | C98: =+C97+B98 -> 62162.013
A99: =+A98+1 -> 93 | B99: =PPMT(0.00604,A99,180,100000,0) -> -537.29159 | C99: =+C98+B99 -> 61624.722
A100: =+A99+1 -> 94 | B100: =PPMT(0.00604,A100,180,100000,0) -> -540.53683 | C100: =+C99+B100 -> 61084.185
...
